quick_hull/__init__.py
quick_hull/quick_hull.py
quick_hull/utils.py
quick_hull-0.1.1.dist-info/LICENSE
quick_hull-0.1.1.dist-info/METADATA
quick_hull-0.1.1.dist-info/WHEEL
quick_hull-0.1.1.dist-info/top_level.txt
quick_hull-0.1.1.dist-info/RECORD
